video_frame_extractor/__init__.py
video_frame_extractor/cli.py
video_frame_extractor/extractor.py
framesnap-1.0.0.dist-info/METADATA
framesnap-1.0.0.dist-info/WHEEL
framesnap-1.0.0.dist-info/entry_points.txt
framesnap-1.0.0.dist-info/top_level.txt
framesnap-1.0.0.dist-info/RECORD
